{
    "api": "transformers.ChineseCLIPModel.get_image_features",
    "type": "function",
    "version": "main",
    "args_list": [
        "pixel_values:",
        "typing.Optional[torch.FloatTensor]",
        "output_attentions",
        "output_hidden_states",
        "interpolate_pos_encoding",
        "return_dict",
        ")"
    ],
    "params": [
        {
            "name": "pixel_values",
            "type": "torch.FloatTensor of shape (batch_size, num_channels, height, width)",
            "optional": false,
            "default": "",
            "description": "Pixel values. Padding will be ignored by default should you provide it. Pixel values can be obtained usingAutoImageProcessor. See ChineseCLIPImageProcessor.call() for details."
        },
        {
            "name": "output_attentions",
            "type": "bool",
            "optional": true,
            "default": "",
            "description": "Whether or not to return the attentions tensors of all attention layers. See attentions under returnedtensors for more detail."
        },
        {
            "name": "output_hidden_states",
            "type": "bool",
            "optional": true,
            "default": "",
            "description": "Whether or not to return the hidden states of all layers. See hidden_states under returned tensors formore detail."
        },
        {
            "name": "interpolate_pos_encoding",
            "type": "bool",
            "optional": true,
            "default": "",
            "description": "Whether to interpolate the pre-trained position encodings."
        },
        {
            "name": "return_dict",
            "type": "bool",
            "optional": true,
            "default": "",
            "description": "Whether or not to return a ModelOutput instead of a plain tuple."
        }
    ],
    "return": "image_features (torch.FloatTensor of shape (batch_size, output_dim)"
}